{
  "general": {
    "label": "General",
    "icon": "fa-gear",
    "options": {
      "strings": {
        "label": "Strings",
        "icon": "fa-bars",
        "options": {
          "six": {
            "label": "6",
            "key": "strings",
            "value": 6,
            "price": 2999
          },
          "seven": {
            "label": "7",
            "key": "strings",
            "value": 7,
            "price": 3149
          },
          "eight": {
            "label": "8",
            "key": "strings",
            "value": 8,
            "price": 3299
          }
        }
      },
      "scale": {
        "label": "Scale",
        "icon": "fa-ruler",
        "options": {
          "standard": {
            "label": "Standard",
            "key": "scale",
            "value": "Standard",
            "price": 0
          },
          "multilscale": {
            "label": "Multi-Scale",
            "key": "scale",
            "value": "Multiscale",
            "price": 100
          }
        }
      }
    }
  },
  "body": {
    "label": "Body",
    "icon": "fa-android",
    "options": {
      "wood": {
        "label": "Wood",
        "icon": "fa-wood",
        "options": {
          "poplar": {
            "label": "Poplar",
            "icon": "",
            "key": "body-wood",
            "value": "poplar",
            "price": 0
          },
          "swamp-ash": {
            "label": "Swamp Ash",
            "icon": "",
            "key": "body-wood",
            "value": "swamp-ash",
            "price": 50
          },
          "mahogany": {
            "label": "Mahogany",
            "icon": "",
            "key": "body-wood",
            "value": "mahogany",
            "price": 50
          },
          "walnut": {
            "label": "Walnut",
            "icon": "",
            "key": "body-wood",
            "value": "walnut",
            "price": 120
          },
          "other": {
            "label": "Other",
            "icon": "",
            "key": "body-wood",
            "value": "other",
            "price": "Inquiry"
          }
        }
      },
      "top-wood": {
        "label": "Top Wood",
        "icon": "",
        "options": {
          "flamed-maple": {
            "label": "Flamed Maple",
            "icon": "",
            "key": "top-wood",
            "value": "flamed-maple",
            "price": 250
          },
          "burled-marple": {
            "label": "Burled Maple",
            "icon": "",
            "key": "top-wood",
            "value": "burled-maple",
            "price": 300
          },
          "figured-koa": {
            "label": "Figured Koa",
            "icon": "",
            "key": "top-wood",
            "value": "figured-koa",
            "price": 350
          },
          "wenge": {
            "label": "Wenge",
            "icon": "",
            "key": "top-wood",
            "value": "wenge",
            "price": 250
          },
          "walnut": {
            "label": "Walnut",
            "icon": "",
            "key": "top-wood",
            "value": "walnut",
            "price": 125
          },
          "other": {
            "label": "Other",
            "icon": "",
            "key": "top-wood",
            "value": "other",
            "price": "Inquiry"
          }
        }
      },
      "finish": {
        "label": "Finish",
        "options": {
          "black-pearl": {
            "label": "Black Pearl",
            "key": "finish",
            "value": "black-pearl",
            "price": 0
          },
          "sports-classic-grey": {
            "label": "Sports Classic Grey",
            "key": "finish",
            "value": "sports-classic-grey",
            "price": 0
          },
          "white-pearl": {
            "label": "White Pearl",
            "key": "finish",
            "value": "white-pearl",
            "price": 0
          }
        }
      }
    }
  },
  "neck": {
    "label": "Neck",
    "icon": "fa-window-restore",
    "options": {
      "wood": {
        "label": "Wood",
        "options": {
          "two-piece-wenge": {
            "label": "2 piece Wenge",
            "key": "neck-wood",
            "value": "2-piece-wenge",
            "price": 0
          },
          "two-piece-maple": {
            "label": "2 piece Maple",
            "key": "neck-wood",
            "value": "2-piece-maple",
            "price": 0
          },
          "two-piece-mahogany": {
            "label": "2 piece Mahogany",
            "key": "neck-wood",
            "value": "2-piece-mahogany",
            "price": 0
          },
          "other": {
            "label": "Other",
            "key": "neck-wood",
            "value": "Other",
            "price": "Inquiry"
          }
        }
      },
      "fingerboard": {
        "label": "Material",
        "options": {
          "katalox": {
            "label": "Katalox",
            "key": "fingerboard",
            "value": "katalox",
            "price": 0
          },
          "richlite": {
            "label": "Richlite",
            "key": "fingerboard",
            "value": "richlite",
            "price": 30
          },
          "rosewood": {
            "label": "Rosewood",
            "key": "fingerboard",
            "value": "rosewood",
            "price": 30
          }
        }
      }
    }
  },
  "headstock": {
    "label": "Headstock",
    "icon": "fa-book",
    "options": {
      "style": {
        "label": "Style",
        "icon": "fa-bars",
        "options": {
          "headstock": {
            "label": "Headstock",
            "key": "headstyle",
            "value": "Headstock",
            "price": 0
          },
          "headless": {
            "label": "Headless",
            "key": "headstyle",
            "value": "Headless",
            "price": 100
          }
        }
      }
    }
  },
  "hardware": {
    "label": "Hardware",
    "icon": "fa-angle-down",
    "options": {
      "color": {
        "label": "Color",
        "options": {
          "chrome": {
            "label": "Chrome",
            "key": "hardware-color",
            "value": "chrome",
            "price": 0
          },
          "black": {
            "label": "Black",
            "key": "hardware-color",
            "value": "black",
            "price": 0
          },
          "gold": {
            "label": "Gold",
            "key": "hardware-color",
            "value": "gold",
            "price": 100
          }
        }
      },
      "fretwire": {
        "label": "Frets",
        "options": {
          "nickel-silver": {
            "label": "Nickel Silver",
            "key": "fretwire",
            "value": "nickel-silver",
            "price": 0
          },
          "custom-nickel": {
            "label": "Custom Gauge Nickel Silver",
            "key": "fretwire",
            "value": "nickel-silver",
            "price": 0            
          },
          "custom-stainless": {
            "label": "Custom Gauge Stainless Steel",
            "key": "fretwire",
            "value": "nickel-silver",
            "price": 0            
          }
        }
      },
      "nut": {
        "label": "Nut Width",
        "options": {
          "custom": {
            "label": "Custom Nut Width",
            "key": "nut-width",
            "value": "custom",
            "price": 100
          }
        }
      }
    }
  },
  "extras": {
    "label": "Extras",
    "icon": "fa-archive"
  }
}